magpy/HOp.py
magpy/QSystem.py
magpy/__init__.py
magpy/methods.py
magpy-1.0.0.dist-info/LICENSE.md
magpy-1.0.0.dist-info/METADATA
magpy-1.0.0.dist-info/WHEEL
magpy-1.0.0.dist-info/top_level.txt
magpy-1.0.0.dist-info/RECORD
